LICENSE
MANIFEST.in
README.md
setup.cfg
setup.py
django_exception_blame.egg-info/PKG-INFO
django_exception_blame.egg-info/SOURCES.txt
django_exception_blame.egg-info/dependency_links.txt
django_exception_blame.egg-info/requires.txt
django_exception_blame.egg-info/top_level.txt
exceptionblame/__init__.py
exceptionblame/middleware.py