Metadata-Version: 1.1
Name: django-exception-blame
Version: 0.1.1
Summary: Show blame in a exception.
Home-page: https://github.com/gdelfresno/django-exception-blame
Author: gdelfresno
Author-email: gdelfrenso@gmail.com
License: MIT
Download-URL: https://github.com/gdelfresno/django-exception-blame/tarball/0.1
Platform: UNKNOWN
Classifier: Environment :: Web Environment
Classifier: Framework :: Django
Classifier: Intended Audience :: Developers
Classifier: License :: OSI Approved :: MIT License
Classifier: Operating System :: OS Independent
Classifier: Programming Language :: Python
Classifier: Topic :: Internet :: WWW/HTTP
Classifier: Topic :: Internet :: WWW/HTTP :: Dynamic Content
Classifier: Topic :: Software Development :: Version Control
